xlpkg/__init__.py
xlpkg/dj_u.py
xlpkg/pub.py
xlpkg/pyproject.toml
xlpkg/q.py
xlpkg/ruff00.toml
xlpkg/test_x.py
xlpkg/x.py
xlpkg/x1.py
xlpkg/x2.py
xlpkg/x6.py
xlpkg/x60.py
xlpkg/y.py
xlpkg-1.0.0.137.dist-info/METADATA
xlpkg-1.0.0.137.dist-info/WHEEL
xlpkg-1.0.0.137.dist-info/RECORD
