Metadata-Version: 2.3
Name: xlpkg
Version: 1.0.0.137
Summary: include xq.p y.py y.py pub.py
License: MIT
Author: xiaolong
Author-email: longx888@126.com
Requires-Python: >=3.12
Classifier: License :: OSI Approved :: MIT License
Classifier: Programming Language :: Python :: 3
Classifier: Programming Language :: Python :: 3.12
Classifier: Programming Language :: Python :: 3.13
Requires-Dist: click (>=8.0.0,<9.0.0)
Requires-Dist: flask (>=3.0.3,<4.0.0)
Requires-Dist: pymysql (>=1.1.1,<2.0.0)
Requires-Dist: requests (>=2.31.0,<3.0.0)
Requires-Dist: xlwt (>=1.3.0,<2.0.0)
Project-URL: Repository, https://gitee.com/dellcell/xlpkg
